lsp_devtools/__init__.py
lsp_devtools/__main__.py
lsp_devtools/cli.py
lsp_devtools/database.py
lsp_devtools/py.typed
lsp_devtools/agent/__init__.py
lsp_devtools/agent/agent.py
lsp_devtools/agent/client.py
lsp_devtools/agent/protocol.py
lsp_devtools/agent/server.py
lsp_devtools/client/__init__.py
lsp_devtools/client/app.css
lsp_devtools/client/lsp.py
lsp_devtools/client/editor/__init__.py
lsp_devtools/client/editor/completion.py
lsp_devtools/client/editor/text_editor.py
lsp_devtools/handlers/__init__.py
lsp_devtools/handlers/dbinit.sql
lsp_devtools/handlers/sql.py
lsp_devtools/inspector/__init__.py
lsp_devtools/inspector/app.css
lsp_devtools/record/__init__.py
lsp_devtools/record/filters.py
lsp_devtools/record/formatters.py
lsp_devtools/record/visualize.py
lsp_devtools-0.2.4.dist-info/METADATA
lsp_devtools-0.2.4.dist-info/WHEEL
lsp_devtools-0.2.4.dist-info/entry_points.txt
lsp_devtools-0.2.4.dist-info/licenses/LICENSE
lsp_devtools-0.2.4.dist-info/RECORD
