Metadata-Version: 2.3
Name: lsp-devtools
Version: 0.2.4
Summary: Developer tooling for language servers
Project-URL: Bug Tracker, https://github.com/swyddfa/lsp-devtools/issues
Project-URL: Documentation, https://lsp-devtools.readthedocs.io/en/latest/
Project-URL: Source Code, https://github.com/swyddfa/lsp-devtools
Author-email: Alex Carney <alcarneyme@gmail.com>
License: MIT
Classifier: Development Status :: 3 - Alpha
Classifier: License :: OSI Approved :: MIT License
Classifier: Programming Language :: Python
Classifier: Programming Language :: Python :: 3
Classifier: Programming Language :: Python :: 3 :: Only
Classifier: Programming Language :: Python :: 3.9
Classifier: Programming Language :: Python :: 3.10
Classifier: Programming Language :: Python :: 3.11
Classifier: Programming Language :: Python :: 3.12
Requires-Python: >=3.9
Requires-Dist: aiosqlite
Requires-Dist: platformdirs
Requires-Dist: pygls>=2.0a2
Requires-Dist: stamina
Requires-Dist: textual>=0.41.0
